{"videoId":236338793,"videoName":"Men's Event 1, Björgvin Karl Guđmundsson, 4_10.mp4","createdAt":"2022-02-28T22:10:44.078Z","updatedAt":"2022-02-28T22:10:44.078Z","description":"","tags":[{"name":"chest-to-bar","id":118517275,"tagId":30139579,"frameRange":[1484,1502],"labelerLogin":"plaguss","createdAt":"2022-03-01T19:11:57.538Z","updatedAt":"2022-03-01T19:11:57.538Z"},{"name":"thruster","id":118517271,"tagId":30139578,"frameRange":[301,327],"labelerLogin":"plaguss","createdAt":"2022-03-01T19:10:23.983Z","updatedAt":"2022-03-01T19:10:23.983Z"},{"name":"chest-to-bar","id":118517955,"tagId":30139579,"frameRange":[7165,7186],"labelerLogin":"plaguss","createdAt":"2022-03-01T19:29:39.783Z","updatedAt":"2022-03-01T19:29:39.783Z"},{"name":"thruster","id":118517282,"tagId":30139578,"frameRange":[2572,2600],"labelerLogin":"plaguss","createdAt":"2022-03-01T19:14:43.322Z","updatedAt":"2022-03-01T19:14:43.322Z"},{"name":"thruster","id":118517280,"tagId":30139578,"frameRange":[2463,2490],"labelerLogin":"plaguss","createdAt":"2022-03-01T19:14:16.255Z","updatedAt":"2022-03-01T19:14:16.255Z"},{"name":"thruster","id":118517284,"tagId":30139578,"frameRange":[3817,3817],"labelerLogin":"plaguss","createdAt":"2022-03-01T19:15:26.691Z","updatedAt":"2022-03-01T19:15:26.691Z"},{"name":"chest-to-bar","id":118517274,"tagId":30139579,"frameRange":[1414,1471],"labelerLogin":"plaguss","createdAt":"2022-03-01T19:11:45.788Z","updatedAt":"2022-03-01T19:11:45.788Z"},{"name":"thruster","id":118517272,"tagId":30139578,"frameRange":[350,378],"labelerLogin":"plaguss","createdAt":"2022-03-01T19:10:42.235Z","updatedAt":"2022-03-01T19:10:42.235Z"},{"name":"thruster","id":118517273,"tagId":30139578,"frameRange":[402,427],"labelerLogin":"plaguss","createdAt":"2022-03-01T19:11:02.091Z","updatedAt":"2022-03-01T19:11:02.091Z"},{"name":"thruster","id":118517269,"tagId":30139578,"frameRange":[200,225],"labelerLogin":"plaguss","createdAt":"2022-03-01T19:09:57.082Z","updatedAt":"2022-03-01T19:09:57.082Z"},{"name":"thruster","id":118517270,"tagId":30139578,"frameRange":[249,275],"labelerLogin":"plaguss","createdAt":"2022-03-01T19:10:11.698Z","updatedAt":"2022-03-01T19:10:11.698Z"},{"name":"thruster","id":118517297,"tagId":30139578,"frameRange":[4836,4863],"labelerLogin":"plaguss","createdAt":"2022-03-01T19:18:42.169Z","updatedAt":"2022-03-01T19:18:42.169Z"},{"name":"chest-to-bar","id":118517276,"tagId":30139579,"frameRange":[1516,1537],"labelerLogin":"plaguss","createdAt":"2022-03-01T19:12:01.868Z","updatedAt":"2022-03-01T19:12:01.868Z"},{"name":"chest-to-bar","id":118517277,"tagId":30139579,"frameRange":[1549,1567],"labelerLogin":"plaguss","createdAt":"2022-03-01T19:12:36.823Z","updatedAt":"2022-03-01T19:12:36.823Z"},{"name":"chest-to-bar","id":118517278,"tagId":30139579,"frameRange":[1580,1602],"labelerLogin":"plaguss","createdAt":"2022-03-01T19:13:08.462Z","updatedAt":"2022-03-01T19:13:08.462Z"},{"name":"thruster","id":118517279,"tagId":30139578,"frameRange":[2408,2436],"labelerLogin":"plaguss","createdAt":"2022-03-01T19:13:45.265Z","updatedAt":"2022-03-01T19:13:45.265Z"},{"name":"chest-to-bar","id":118517288,"tagId":30139579,"frameRange":[3931,3951],"labelerLogin":"plaguss","createdAt":"2022-03-01T19:16:59.567Z","updatedAt":"2022-03-01T19:16:59.567Z"},{"name":"thruster","id":118517281,"tagId":30139578,"frameRange":[2518,2546],"labelerLogin":"plaguss","createdAt":"2022-03-01T19:14:28.466Z","updatedAt":"2022-03-01T19:14:28.466Z"},{"name":"chest-to-bar","id":118517285,"tagId":30139579,"frameRange":[3833,3853],"labelerLogin":"plaguss","createdAt":"2022-03-01T19:15:50.875Z","updatedAt":"2022-03-01T19:15:50.875Z"},{"name":"chest-to-bar","id":118517286,"tagId":30139579,"frameRange":[3867,3886],"labelerLogin":"plaguss","createdAt":"2022-03-01T19:16:30.849Z","updatedAt":"2022-03-01T19:16:30.849Z"},{"name":"chest-to-bar","id":118517287,"tagId":30139579,"frameRange":[3899,3918],"labelerLogin":"plaguss","createdAt":"2022-03-01T19:16:47.576Z","updatedAt":"2022-03-01T19:16:47.576Z"},{"name":"thruster","id":118517298,"tagId":30139578,"frameRange":[4890,4916],"labelerLogin":"plaguss","createdAt":"2022-03-01T19:18:53.395Z","updatedAt":"2022-03-01T19:18:53.395Z"},{"name":"chest-to-bar","id":118517289,"tagId":30139579,"frameRange":[3964,3983],"labelerLogin":"plaguss","createdAt":"2022-03-01T19:17:09.996Z","updatedAt":"2022-03-01T19:17:09.996Z"},{"name":"chest-to-bar","id":118517957,"tagId":30139579,"frameRange":[7233,7252],"labelerLogin":"plaguss","createdAt":"2022-03-01T19:30:15.076Z","updatedAt":"2022-03-01T19:30:15.076Z"},{"name":"thruster","id":118517290,"tagId":30139578,"frameRange":[4716,4745],"labelerLogin":"plaguss","createdAt":"2022-03-01T19:17:38.387Z","updatedAt":"2022-03-01T19:17:38.387Z"},{"name":"thruster","id":118517296,"tagId":30139578,"frameRange":[4783,4810],"labelerLogin":"plaguss","createdAt":"2022-03-01T19:18:27.452Z","updatedAt":"2022-03-01T19:18:27.452Z"},{"name":"thruster","id":118517299,"tagId":30139578,"frameRange":[4943,4971],"labelerLogin":"plaguss","createdAt":"2022-03-01T19:19:09.741Z","updatedAt":"2022-03-01T19:19:09.741Z"},{"name":"chest-to-bar","id":118517954,"tagId":30139579,"frameRange":[7133,7152],"labelerLogin":"plaguss","createdAt":"2022-03-01T19:29:30.367Z","updatedAt":"2022-03-01T19:29:30.367Z"},{"name":"chest-to-bar","id":118517953,"tagId":30139579,"frameRange":[7065,7119],"labelerLogin":"plaguss","createdAt":"2022-03-01T19:29:01.773Z","updatedAt":"2022-03-01T19:29:01.773Z"},{"name":"chest-to-bar","id":118517956,"tagId":30139579,"frameRange":[7199,7219],"labelerLogin":"plaguss","createdAt":"2022-03-01T19:30:00.311Z","updatedAt":"2022-03-01T19:30:00.311Z"},{"name":"thruster","id":118517283,"tagId":30139578,"frameRange":[2624,2652],"labelerLogin":"plaguss","createdAt":"2022-03-01T19:14:55.570Z","updatedAt":"2022-03-01T19:14:55.570Z"}],"objects":[],"size":{"height":480,"width":854},"framesCount":7848,"frames":[]}